api_client/__init__.py
api_client/api/__init__.py
api_client/api/default/__init__.py
api_client/api/default/accesstoken_create.py
api_client/api/default/accesstoken_delete.py
api_client/api/default/accesstoken_list.py
api_client/api/default/usage_show.py
api_client/client.py
api_client/errors.py
api_client/models/__init__.py
api_client/models/body_create_access_token_v0_accesstoken_create_post.py
api_client/models/body_delete_access_token_v0_accesstoken_delete_post.py
api_client/models/http_validation_error.py
api_client/models/validation_error.py
api_client/py.typed
api_client/types.py
cli/__init__.py
cli/config.py
cli/main.py
cli/util.py
zebrastream_cli-0.0.1.dist-info/LICENSE
zebrastream_cli-0.0.1.dist-info/METADATA
zebrastream_cli-0.0.1.dist-info/WHEEL
zebrastream_cli-0.0.1.dist-info/entry_points.txt
zebrastream_cli-0.0.1.dist-info/RECORD
