Metadata-Version: 2.3
Name: zebrastream-cli
Version: 0.0.1
Summary: An open-source CLI for managing ZebraStream accounts.
License: GPL-3.0-or-later
Author: Johannes Dröge
Author-email: p5p129dw@parsimonit.com
Requires-Python: >=3.9,<4.0
Classifier: License :: OSI Approved :: GNU General Public License v3 or later (GPLv3+)
Classifier: Programming Language :: Python :: 3
Classifier: Programming Language :: Python :: 3.9
Classifier: Programming Language :: Python :: 3.10
Classifier: Programming Language :: Python :: 3.11
Classifier: Programming Language :: Python :: 3.12
Classifier: Programming Language :: Python :: 3.13
Requires-Dist: attrs (>=22.2.0)
Requires-Dist: click (>=8.1.7)
Requires-Dist: confuse (>=2.0.1,<3.0.0)
Requires-Dist: httpx (>=0.23.0,<0.29.0)
Requires-Dist: python-dateutil (>=2.8.0,<3.0.0)
Requires-Dist: rich (>=13.0.0,<14.0.0)
Requires-Dist: typer[all] (>=0.16.0,<0.17.0)
